encrypted_dns/__init__.py
encrypted_dns/config.py
encrypted_dns/main.py
encrypted_dns/utils.py
encrypted_dns/inbound/__init__.py
encrypted_dns/inbound/tcp.py
encrypted_dns/inbound/udp.py
encrypted_dns/outbound/__init__.py
encrypted_dns/outbound/https.py
encrypted_dns/outbound/tcp.py
encrypted_dns/outbound/tls.py
encrypted_dns/outbound/udp.py
encrypted_dns/resolve/__init__.py
encrypted_dns/resolve/cache.py
encrypted_dns/resolve/core.py
encrypted_dns-1.2.0.dist-info/LICENSE
encrypted_dns-1.2.0.dist-info/METADATA
encrypted_dns-1.2.0.dist-info/WHEEL
encrypted_dns-1.2.0.dist-info/entry_points.txt
encrypted_dns-1.2.0.dist-info/top_level.txt
encrypted_dns-1.2.0.dist-info/RECORD
