Metadata-Version: 2.1
Name: encrypted-dns
Version: 1.2.0
Summary: DNS-over-HTTPS and DNS-over-TLS server and forwarder.
Home-page: https://github.com/Berkeley-Reject/Encrypted-DNS
Author: Xiaoyang Liu
Author-email: siujoeng.lau@gmail.com
License: Apache 2.0
Keywords: dns doh dot tls https
Platform: UNKNOWN
Classifier: Programming Language :: Python :: 3
Classifier: License :: OSI Approved :: Apache Software License
Classifier: Topic :: Internet :: Name Service (DNS)
Classifier: Topic :: Security :: Cryptography
Classifier: Topic :: Utilities
Requires-Python: >=3.6
Requires-Dist: dnspython
Requires-Dist: requests
